MANIFEST.in
README.rst
setup.py
docs/CHANGELOG.rst
docs/LICENSE.rst
docs/api.rst
docs/conf.py
docs/glossary.rst
docs/index.rst
docs/_static/.gitkeep
redturtle/__init__.py
redturtle.prepoverlays.egg-info/PKG-INFO
redturtle.prepoverlays.egg-info/SOURCES.txt
redturtle.prepoverlays.egg-info/dependency_links.txt
redturtle.prepoverlays.egg-info/entry_points.txt
redturtle.prepoverlays.egg-info/namespace_packages.txt
redturtle.prepoverlays.egg-info/not-zip-safe
redturtle.prepoverlays.egg-info/requires.txt
redturtle.prepoverlays.egg-info/top_level.txt
redturtle/prepoverlays/__init__.py
redturtle/prepoverlays/configure.zcml
redturtle/prepoverlays/interfaces.py
redturtle/prepoverlays/testing.py
redturtle/prepoverlays/browser/__init__.py
redturtle/prepoverlays/browser/configure.zcml
redturtle/prepoverlays/browser/static/.gitkeep
redturtle/prepoverlays/browser/static/overlays.js
redturtle/prepoverlays/profiles/default/browserlayer.xml
redturtle/prepoverlays/profiles/default/jsregistry.xml
redturtle/prepoverlays/profiles/default/metadata.xml
redturtle/prepoverlays/tests/__init__.py
redturtle/prepoverlays/tests/configure.zcml
redturtle/prepoverlays/tests/test_setup.py
redturtle/prepoverlays/tests/templates/test_redturtle_overlays.pt
redturtle/prepoverlays/upgrades/__init__.py
redturtle/prepoverlays/upgrades/configure.zcml