Metadata-Version: 1.1
Name: redturtle.prepoverlays
Version: 1.0.0
Summary: Trigger Plone overlays by using data attributes
Home-page: http://pypi.python.org/pypi/redturtle.prepoverlays
Author: RedTurtle Technology
Author-email: sviluppoplone@redturtle.it
License: GPL
Keywords: Plone
Platform: UNKNOWN
Classifier: Framework :: Plone
Classifier: Framework :: Plone :: 4.3
Classifier: Framework :: Plone :: 4.2
Classifier: Programming Language :: Python
Classifier: License :: OSI Approved :: GNU General Public License (GPL)
Classifier: Programming Language :: Python
Classifier: Programming Language :: Python :: 2.7
